{
  "as_of": "2026-06-01T22:00:02.724932+00:00",
  "date": "2026-06-01",
  "version": "edge-alerts-v1",
  "sports": [
    "MLB"
  ],
  "summary": {
    "model_edges": 6,
    "book_discrepancies": 0,
    "line_movements": 0,
    "warnings": []
  },
  "model_edges": [
    {
      "sport": "MLB",
      "game_id": "mlb_2026-06-01_mia_wsh_total",
      "game": "Miami Marlins at Washington Nationals",
      "market": "total",
      "side": "Over 8.0",
      "best_book": "FanDuel",
      "market_odds": "-110",
      "model_fair_line": "-191",
      "model_probability": 0.6562,
      "market_probability": 0.52381,
      "edge": 0.1324,
      "ev": 0.252745,
      "tier": "A",
      "signal": "Copacetic Edge",
      "model_alignment": "Model-backed",
      "updated_at": "2026-06-01T22:00:02.724932+00:00"
    },
    {
      "sport": "MLB",
      "game_id": "mlb_2026-06-01_mia_wsh_run_line",
      "game": "Miami Marlins at Washington Nationals",
      "market": "run line",
      "side": "Washington Nationals -1.5",
      "best_book": "FanDuel",
      "market_odds": "+146",
      "model_fair_line": "-108",
      "model_probability": 0.5191,
      "market_probability": 0.406504,
      "edge": 0.1126,
      "ev": 0.276986,
      "tier": "A",
      "signal": "Copacetic Edge",
      "model_alignment": "Model-backed",
      "updated_at": "2026-06-01T22:00:02.724932+00:00"
    },
    {
      "sport": "MLB",
      "game_id": "mlb_2026-06-01_nym_sea_moneyline",
      "game": "New York Mets at Seattle Mariners",
      "market": "moneyline",
      "side": "New York Mets",
      "best_book": "FanDuel",
      "market_odds": "+114",
      "model_fair_line": "-136",
      "model_probability": 0.5768,
      "market_probability": 0.46729,
      "edge": 0.1095,
      "ev": 0.234352,
      "tier": "A",
      "signal": "Copacetic Edge",
      "model_alignment": "Model-backed",
      "updated_at": "2026-06-01T22:00:02.724932+00:00"
    },
    {
      "sport": "MLB",
      "game_id": "mlb_2026-06-01_sf_mil_run_line",
      "game": "San Francisco Giants at Milwaukee Brewers",
      "market": "run line",
      "side": "Milwaukee Brewers -1.5",
      "best_book": "FanDuel",
      "market_odds": "+146",
      "model_fair_line": "-105",
      "model_probability": 0.5119,
      "market_probability": 0.406504,
      "edge": 0.1054,
      "ev": 0.259274,
      "tier": "A",
      "signal": "Copacetic Edge",
      "model_alignment": "Model-backed",
      "updated_at": "2026-06-01T22:00:02.724932+00:00"
    },
    {
      "sport": "MLB",
      "game_id": "mlb_2026-06-01_kc_cin_total",
      "game": "Kansas City Royals at Cincinnati Reds",
      "market": "total",
      "side": "Over 8.5",
      "best_book": "FanDuel",
      "market_odds": "-110",
      "model_fair_line": "-157",
      "model_probability": 0.6114,
      "market_probability": 0.52381,
      "edge": 0.0876,
      "ev": 0.167218,
      "tier": "A",
      "signal": "Copacetic Edge",
      "model_alignment": "Model-backed",
      "updated_at": "2026-06-01T22:00:02.724932+00:00"
    },
    {
      "sport": "MLB",
      "game_id": "mlb_2026-06-01_nym_sea_run_line",
      "game": "New York Mets at Seattle Mariners",
      "market": "run line",
      "side": "New York Mets +1.5",
      "best_book": "FanDuel",
      "market_odds": "-205",
      "model_fair_line": "-302",
      "model_probability": 0.7511,
      "market_probability": 0.672131,
      "edge": 0.079,
      "ev": 0.11749,
      "tier": "A",
      "signal": "Copacetic Edge",
      "model_alignment": "Model-backed",
      "updated_at": "2026-06-01T22:00:02.724932+00:00"
    }
  ],
  "book_discrepancies": [],
  "line_movements": []
}
