{
  "as_of": "2026-06-26T00:30:01.534162+00:00",
  "date": "2026-06-25",
  "version": "edge-alerts-v1",
  "sports": [
    "MLB"
  ],
  "summary": {
    "model_edges": 4,
    "book_discrepancies": 9,
    "line_movements": 15,
    "warnings": []
  },
  "model_edges": [
    {
      "sport": "MLB",
      "game_id": "mlb_2026-06-25_sea_pit_run_line",
      "game": "Seattle Mariners at Pittsburgh Pirates",
      "market": "run line",
      "side": "Pittsburgh Pirates +1.5",
      "best_book": "DraftKings",
      "market_odds": "-141",
      "model_fair_line": "-381",
      "model_probability": 0.792,
      "market_probability": 0.585062,
      "edge": 0.2069,
      "ev": 0.353702,
      "tier": "A",
      "signal": "Copacetic Edge",
      "model_alignment": "Model-backed",
      "updated_at": "2026-06-26T00:30:01.534162+00:00"
    },
    {
      "sport": "MLB",
      "game_id": "mlb_2026-06-25_sea_pit_moneyline",
      "game": "Seattle Mariners at Pittsburgh Pirates",
      "market": "moneyline",
      "side": "Pittsburgh Pirates",
      "best_book": "DraftKings",
      "market_odds": "+119",
      "model_fair_line": "-191",
      "model_probability": 0.6562,
      "market_probability": 0.456621,
      "edge": 0.1996,
      "ev": 0.437078,
      "tier": "A",
      "signal": "Copacetic Edge",
      "model_alignment": "Model-backed",
      "updated_at": "2026-06-26T00:30:01.534162+00:00"
    },
    {
      "sport": "MLB",
      "game_id": "mlb_2026-06-25_hou_det_run_line",
      "game": "Houston Astros at Detroit Tigers",
      "market": "run line",
      "side": "Detroit Tigers +1.5",
      "best_book": "DraftKings",
      "market_odds": "-189",
      "model_fair_line": "-278",
      "model_probability": 0.7355,
      "market_probability": 0.653979,
      "edge": 0.0815,
      "ev": 0.124653,
      "tier": "A",
      "signal": "Copacetic Edge",
      "model_alignment": "Model-backed",
      "updated_at": "2026-06-26T00:30:01.534162+00:00"
    },
    {
      "sport": "MLB",
      "game_id": "mlb_2026-06-25_phi_wsh_run_line",
      "game": "Philadelphia Phillies at Washington Nationals",
      "market": "run line",
      "side": "Washington Nationals +1.5",
      "best_book": "DraftKings",
      "market_odds": "-115",
      "model_fair_line": "-154",
      "model_probability": 0.6059,
      "market_probability": 0.534884,
      "edge": 0.071,
      "ev": 0.13277,
      "tier": "A",
      "signal": "Copacetic Edge",
      "model_alignment": "Model-backed",
      "updated_at": "2026-06-26T00:30:01.534162+00:00"
    }
  ],
  "book_discrepancies": [
    {
      "sport": "MLB",
      "game_id": "mlb_2026-06-25_phi_wsh_disc",
      "game": "Philadelphia Phillies at Washington Nationals",
      "market": "moneyline",
      "outcomes": [
        {
          "outcome": "Philadelphia Phillies",
          "book": "LowVig.ag",
          "odds": "-161",
          "decimal_odds": 1.6211
        },
        {
          "outcome": "Washington Nationals",
          "book": "BetRivers",
          "odds": "+150",
          "decimal_odds": 2.5
        }
      ],
      "implied_probability_sum": 1.016858,
      "arb_return": -0.016858,
      "signal": "Near-Arb",
      "model_alignment": "Model-backed",
      "updated_at": "2026-06-26T00:30:01.534162+00:00"
    },
    {
      "sport": "MLB",
      "game_id": "mlb_2026-06-25_nyy_bos_disc",
      "game": "New York Yankees at Boston Red Sox",
      "market": "moneyline",
      "outcomes": [
        {
          "outcome": "New York Yankees",
          "book": "LowVig.ag",
          "odds": "-142",
          "decimal_odds": 1.7042
        },
        {
          "outcome": "Boston Red Sox",
          "book": "BetUS",
          "odds": "+132",
          "decimal_odds": 2.32
        }
      ],
      "implied_probability_sum": 1.017811,
      "arb_return": -0.017811,
      "signal": "Near-Arb",
      "model_alignment": "Not model-backed",
      "updated_at": "2026-06-26T00:30:01.534162+00:00"
    },
    {
      "sport": "MLB",
      "game_id": "mlb_2026-06-25_ath_sf_disc",
      "game": "Athletics at San Francisco Giants",
      "market": "moneyline",
      "outcomes": [
        {
          "outcome": "Athletics",
          "book": "BetUS",
          "odds": "+117",
          "decimal_odds": 2.17
        },
        {
          "outcome": "San Francisco Giants",
          "book": "FanDuel",
          "odds": "-126",
          "decimal_odds": 1.7937
        }
      ],
      "implied_probability_sum": 1.018352,
      "arb_return": -0.018352,
      "signal": "Near-Arb",
      "model_alignment": "Not model-backed",
      "updated_at": "2026-06-26T00:30:01.534162+00:00"
    },
    {
      "sport": "MLB",
      "game_id": "mlb_2026-06-25_chc_nym_disc",
      "game": "Chicago Cubs at New York Mets",
      "market": "moneyline",
      "outcomes": [
        {
          "outcome": "Chicago Cubs",
          "book": "LowVig.ag",
          "odds": "-102",
          "decimal_odds": 1.9804
        },
        {
          "outcome": "New York Mets",
          "book": "BetUS",
          "odds": "-106",
          "decimal_odds": 1.9434
        }
      ],
      "implied_probability_sum": 1.019514,
      "arb_return": -0.019514,
      "signal": "Near-Arb",
      "model_alignment": "Not model-backed",
      "updated_at": "2026-06-26T00:30:01.534162+00:00"
    },
    {
      "sport": "MLB",
      "game_id": "mlb_2026-06-25_hou_det_disc",
      "game": "Houston Astros at Detroit Tigers",
      "market": "moneyline",
      "outcomes": [
        {
          "outcome": "Houston Astros",
          "book": "BetOnline.ag",
          "odds": "+101",
          "decimal_odds": 2.01
        },
        {
          "outcome": "Detroit Tigers",
          "book": "FanDuel",
          "odds": "-110",
          "decimal_odds": 1.9091
        }
      ],
      "implied_probability_sum": 1.021322,
      "arb_return": -0.021322,
      "signal": "Near-Arb",
      "model_alignment": "Model-backed",
      "updated_at": "2026-06-26T00:30:01.534162+00:00"
    },
    {
      "sport": "MLB",
      "game_id": "mlb_2026-06-25_sea_pit_disc",
      "game": "Seattle Mariners at Pittsburgh Pirates",
      "market": "moneyline",
      "outcomes": [
        {
          "outcome": "Seattle Mariners",
          "book": "BetUS",
          "odds": "-141",
          "decimal_odds": 1.7092
        },
        {
          "outcome": "Pittsburgh Pirates",
          "book": "LowVig.ag",
          "odds": "+129",
          "decimal_odds": 2.29
        }
      ],
      "implied_probability_sum": 1.021743,
      "arb_return": -0.021743,
      "signal": "Near-Arb",
      "model_alignment": "Model-backed",
      "updated_at": "2026-06-26T00:30:01.534162+00:00"
    },
    {
      "sport": "MLB",
      "game_id": "mlb_2026-06-25_ari_stl_disc",
      "game": "Arizona Diamondbacks at St. Louis Cardinals",
      "market": "moneyline",
      "outcomes": [
        {
          "outcome": "Arizona Diamondbacks",
          "book": "BetUS",
          "odds": "+118",
          "decimal_odds": 2.18
        },
        {
          "outcome": "St. Louis Cardinals",
          "book": "LowVig.ag",
          "odds": "-129",
          "decimal_odds": 1.7752
        }
      ],
      "implied_probability_sum": 1.022034,
      "arb_return": -0.022034,
      "signal": "Near-Arb",
      "model_alignment": "Not model-backed",
      "updated_at": "2026-06-26T00:30:01.534162+00:00"
    },
    {
      "sport": "MLB",
      "game_id": "mlb_2026-06-25_kc_tb_disc",
      "game": "Kansas City Royals at Tampa Bay Rays",
      "market": "moneyline",
      "outcomes": [
        {
          "outcome": "Kansas City Royals",
          "book": "LowVig.ag",
          "odds": "+126",
          "decimal_odds": 2.26
        },
        {
          "outcome": "Tampa Bay Rays",
          "book": "FanDuel",
          "odds": "-138",
          "decimal_odds": 1.7246
        }
      ],
      "implied_probability_sum": 1.02231,
      "arb_return": -0.02231,
      "signal": "Near-Arb",
      "model_alignment": "Not model-backed",
      "updated_at": "2026-06-26T00:30:01.534162+00:00"
    },
    {
      "sport": "MLB",
      "game_id": "mlb_2026-06-25_tex_tor_disc",
      "game": "Texas Rangers at Toronto Blue Jays",
      "market": "moneyline",
      "outcomes": [
        {
          "outcome": "Texas Rangers",
          "book": "LowVig.ag",
          "odds": "+134",
          "decimal_odds": 2.34
        },
        {
          "outcome": "Toronto Blue Jays",
          "book": "LowVig.ag",
          "odds": "-148",
          "decimal_odds": 1.6757
        }
      ],
      "implied_probability_sum": 1.024125,
      "arb_return": -0.024125,
      "signal": "Near-Arb",
      "model_alignment": "Not model-backed",
      "updated_at": "2026-06-26T00:30:01.534162+00:00"
    }
  ],
  "line_movements": [
    {
      "sport": "MLB",
      "game_id": "mlb_2026-06-25_phi_wsh_lm",
      "game": "Philadelphia Phillies at Washington Nationals",
      "market": "moneyline",
      "side": "Philadelphia Phillies",
      "open_odds": "-174",
      "current_odds": "-205",
      "move": "-31",
      "direction": "Neutral",
      "model_fair_line": "N/A",
      "signal": "Market Movement",
      "alert": "Steam",
      "updated_at": "2026-06-26T00:30:01.534162+00:00"
    },
    {
      "sport": "MLB",
      "game_id": "mlb_2026-06-25_phi_wsh_lm",
      "game": "Philadelphia Phillies at Washington Nationals",
      "market": "moneyline",
      "side": "Washington Nationals",
      "open_odds": "+143",
      "current_odds": "+158",
      "move": "+15",
      "direction": "Neutral",
      "model_fair_line": "N/A",
      "signal": "Market Movement",
      "alert": "Steam",
      "updated_at": "2026-06-26T00:30:01.534162+00:00"
    },
    {
      "sport": "MLB",
      "game_id": "mlb_2026-06-25_tex_tor_lm",
      "game": "Texas Rangers at Toronto Blue Jays",
      "market": "moneyline",
      "side": "Toronto Blue Jays",
      "open_odds": "-156",
      "current_odds": "-104",
      "move": "+52",
      "direction": "Neutral",
      "model_fair_line": "N/A",
      "signal": "Market Movement",
      "alert": "Steam",
      "updated_at": "2026-06-26T00:30:01.534162+00:00"
    },
    {
      "sport": "MLB",
      "game_id": "mlb_2026-06-25_nyy_bos_lm",
      "game": "New York Yankees at Boston Red Sox",
      "market": "moneyline",
      "side": "New York Yankees",
      "open_odds": "-151",
      "current_odds": "-110",
      "move": "+41",
      "direction": "Neutral",
      "model_fair_line": "N/A",
      "signal": "Market Movement",
      "alert": "Steam",
      "updated_at": "2026-06-26T00:30:01.534162+00:00"
    },
    {
      "sport": "MLB",
      "game_id": "mlb_2026-06-25_nyy_bos_lm",
      "game": "New York Yankees at Boston Red Sox",
      "market": "total",
      "side": "Total Line",
      "open_odds": "7.5",
      "current_odds": "8.5",
      "move": "+1.0",
      "direction": "Neutral",
      "model_fair_line": "N/A",
      "signal": "Market Movement",
      "alert": "Drift",
      "updated_at": "2026-06-26T00:30:01.534162+00:00"
    },
    {
      "sport": "MLB",
      "game_id": "mlb_2026-06-25_hou_det_lm",
      "game": "Houston Astros at Detroit Tigers",
      "market": "moneyline",
      "side": "Detroit Tigers",
      "open_odds": "-114",
      "current_odds": "-120",
      "move": "-6",
      "direction": "Neutral",
      "model_fair_line": "N/A",
      "signal": "Market Movement",
      "alert": "Watch",
      "updated_at": "2026-06-26T00:30:01.534162+00:00"
    },
    {
      "sport": "MLB",
      "game_id": "mlb_2026-06-25_hou_det_lm",
      "game": "Houston Astros at Detroit Tigers",
      "market": "total",
      "side": "Total Line",
      "open_odds": "9.0",
      "current_odds": "8.5",
      "move": "-0.5",
      "direction": "Neutral",
      "model_fair_line": "N/A",
      "signal": "Market Movement",
      "alert": "Watch",
      "updated_at": "2026-06-26T00:30:01.534162+00:00"
    },
    {
      "sport": "MLB",
      "game_id": "mlb_2026-06-25_tex_tor_lm",
      "game": "Texas Rangers at Toronto Blue Jays",
      "market": "total",
      "side": "Total Line",
      "open_odds": "8.0",
      "current_odds": "8.5",
      "move": "+0.5",
      "direction": "Neutral",
      "model_fair_line": "N/A",
      "signal": "Market Movement",
      "alert": "Watch",
      "updated_at": "2026-06-26T00:30:01.534162+00:00"
    },
    {
      "sport": "MLB",
      "game_id": "mlb_2026-06-25_chc_nym_lm",
      "game": "Chicago Cubs at New York Mets",
      "market": "moneyline",
      "side": "Chicago Cubs",
      "open_odds": "-108",
      "current_odds": "-110",
      "move": "-2",
      "direction": "Neutral",
      "model_fair_line": "N/A",
      "signal": "Market Movement",
      "alert": "Watch",
      "updated_at": "2026-06-26T00:30:01.534162+00:00"
    },
    {
      "sport": "MLB",
      "game_id": "mlb_2026-06-25_chc_nym_lm",
      "game": "Chicago Cubs at New York Mets",
      "market": "moneyline",
      "side": "New York Mets",
      "open_odds": "-112",
      "current_odds": "-106",
      "move": "+6",
      "direction": "Neutral",
      "model_fair_line": "N/A",
      "signal": "Market Movement",
      "alert": "Watch",
      "updated_at": "2026-06-26T00:30:01.534162+00:00"
    },
    {
      "sport": "MLB",
      "game_id": "mlb_2026-06-25_ari_stl_lm",
      "game": "Arizona Diamondbacks at St. Louis Cardinals",
      "market": "moneyline",
      "side": "Arizona Diamondbacks",
      "open_odds": "+113",
      "current_odds": "+112",
      "move": "-1",
      "direction": "Neutral",
      "model_fair_line": "N/A",
      "signal": "Market Movement",
      "alert": "Watch",
      "updated_at": "2026-06-26T00:30:01.534162+00:00"
    },
    {
      "sport": "MLB",
      "game_id": "mlb_2026-06-25_ari_stl_lm",
      "game": "Arizona Diamondbacks at St. Louis Cardinals",
      "market": "moneyline",
      "side": "St. Louis Cardinals",
      "open_odds": "-136",
      "current_odds": "-132",
      "move": "+4",
      "direction": "Neutral",
      "model_fair_line": "N/A",
      "signal": "Market Movement",
      "alert": "Watch",
      "updated_at": "2026-06-26T00:30:01.534162+00:00"
    },
    {
      "sport": "MLB",
      "game_id": "mlb_2026-06-25_hou_det_lm",
      "game": "Houston Astros at Detroit Tigers",
      "market": "moneyline",
      "side": "Houston Astros",
      "open_odds": "-105",
      "current_odds": "+102",
      "move": "+207",
      "direction": "Neutral",
      "model_fair_line": "N/A",
      "signal": "Market Movement",
      "alert": "Price Flip",
      "updated_at": "2026-06-26T00:30:01.534162+00:00"
    },
    {
      "sport": "MLB",
      "game_id": "mlb_2026-06-25_tex_tor_lm",
      "game": "Texas Rangers at Toronto Blue Jays",
      "market": "moneyline",
      "side": "Texas Rangers",
      "open_odds": "+129",
      "current_odds": "-112",
      "move": "-241",
      "direction": "Neutral",
      "model_fair_line": "N/A",
      "signal": "Market Movement",
      "alert": "Price Flip",
      "updated_at": "2026-06-26T00:30:01.534162+00:00"
    },
    {
      "sport": "MLB",
      "game_id": "mlb_2026-06-25_nyy_bos_lm",
      "game": "New York Yankees at Boston Red Sox",
      "market": "moneyline",
      "side": "Boston Red Sox",
      "open_odds": "+125",
      "current_odds": "-106",
      "move": "-231",
      "direction": "Neutral",
      "model_fair_line": "N/A",
      "signal": "Market Movement",
      "alert": "Price Flip",
      "updated_at": "2026-06-26T00:30:01.534162+00:00"
    }
  ]
}
